clipstack/__init__.py
clipstack/cli.py
clipstack/clipboard.py
clipstack/search.py
clipstack/storage.py
clipstack/tui.py
clipstack-0.1.0.dist-info/licenses/LICENSE
clipstack-0.1.0.dist-info/METADATA
clipstack-0.1.0.dist-info/WHEEL
clipstack-0.1.0.dist-info/entry_points.txt
clipstack-0.1.0.dist-info/top_level.txt
clipstack-0.1.0.dist-info/RECORD
